LoopStructural/__init__.py
LoopStructural/version.py
LoopStructural/datasets/__init__.py
LoopStructural/datasets/_base.py
LoopStructural/datasets/_example_models.py
LoopStructural/datasets/data/claudius.csv
LoopStructural/datasets/data/claudiusbb.txt
LoopStructural/datasets/data/duplex.csv
LoopStructural/datasets/data/duplexbb.txt
LoopStructural/datasets/data/intrusion.csv
LoopStructural/datasets/data/intrusionbb.txt
LoopStructural/datasets/data/onefoldbb.txt
LoopStructural/datasets/data/onefolddata.csv
LoopStructural/datasets/data/refolded_bb.txt
LoopStructural/datasets/data/refolded_fold.csv
LoopStructural/datasets/data/tabular_intrusion.csv
LoopStructural/datasets/data/fault_trace/fault_trace.cpg
LoopStructural/datasets/data/fault_trace/fault_trace.dbf
LoopStructural/datasets/data/fault_trace/fault_trace.prj
LoopStructural/datasets/data/fault_trace/fault_trace.shp
LoopStructural/datasets/data/fault_trace/fault_trace.shx
LoopStructural/datasets/data/geological_map_data/bbox.csv
LoopStructural/datasets/data/geological_map_data/contacts.csv
LoopStructural/datasets/data/geological_map_data/fault_displacement.csv
LoopStructural/datasets/data/geological_map_data/fault_edges.txt
LoopStructural/datasets/data/geological_map_data/fault_locations.csv
LoopStructural/datasets/data/geological_map_data/fault_orientations.csv
LoopStructural/datasets/data/geological_map_data/stratigraphic_order.csv
LoopStructural/datasets/data/geological_map_data/stratigraphic_orientations.csv
LoopStructural/datasets/data/geological_map_data/stratigraphic_thickness.csv
LoopStructural/datatypes/__init__.py
LoopStructural/datatypes/_bounding_box.py
LoopStructural/datatypes/_point.py
LoopStructural/datatypes/_structured_grid.py
LoopStructural/datatypes/_surface.py
LoopStructural/export/exporters.py
LoopStructural/export/file_formats.py
LoopStructural/export/geoh5.py
LoopStructural/export/gocad.py
LoopStructural/export/omf_wrapper.py
LoopStructural/interpolators/__init__.py
loopstructural-1.6.25.dist-info/licenses/LICENSE
loopstructural-1.6.25.dist-info/METADATA
loopstructural-1.6.25.dist-info/WHEEL
loopstructural-1.6.25.dist-info/top_level.txt
loopstructural-1.6.25.dist-info/RECORD
