Metadata-Version: 2.4
Name: LoopStructural
Version: 1.6.25
Summary: 3D geological modelling
Author-email: Lachlan Grose <lachlan.grose@monash.edu>
License: MIT
Project-URL: Documentation, https://Loop3d.org/LoopStructural/
Project-URL: Bug Tracker, https://github.com/loop3d/loopstructural/issues
Project-URL: Source Code, https://github.com/loop3d/loopstructural
Keywords: earth sciences,geology,3-D modelling,structural geology,uncertainty
Classifier: Development Status :: 5 - Production/Stable
Classifier: Intended Audience :: Science/Research
Classifier: Topic :: Scientific/Engineering :: Information Analysis
Classifier: License :: OSI Approved :: MIT License
Classifier: Operating System :: Microsoft :: Windows
Classifier: Operating System :: POSIX
Classifier: Operating System :: MacOS
Classifier: Programming Language :: Python :: 3.8
Classifier: Programming Language :: Python :: 3.9
Classifier: Programming Language :: Python :: 3.10
Classifier: Programming Language :: Python :: 3.11
Classifier: Programming Language :: Python :: 3.12
Requires-Python: >=3.8
License-File: LICENSE
Requires-Dist: numpy>=1.18
Requires-Dist: pandas
Requires-Dist: scipy
Requires-Dist: scikit-image
Requires-Dist: scikit-learn
Provides-Extra: all
Requires-Dist: loopstructural[export,inequalities,jupyter,visualisation]; extra == "all"
Requires-Dist: tqdm; extra == "all"
Provides-Extra: visualisation
Requires-Dist: matplotlib; extra == "visualisation"
Requires-Dist: pyvista; extra == "visualisation"
Requires-Dist: loopstructuralvisualisation>=0.1.14; extra == "visualisation"
Provides-Extra: export
Requires-Dist: geoh5py; extra == "export"
Requires-Dist: pyevtk; extra == "export"
Requires-Dist: dill; extra == "export"
Provides-Extra: jupyter
Requires-Dist: pyvista[all]; extra == "jupyter"
Provides-Extra: inequalities
Requires-Dist: loopsolver; extra == "inequalities"
Provides-Extra: docs
Requires-Dist: pyvista[all]; extra == "docs"
Requires-Dist: pydata-sphinx-theme; extra == "docs"
Requires-Dist: meshio; extra == "docs"
Requires-Dist: loopstructuralvisualisation[all]; extra == "docs"
Requires-Dist: networkx; extra == "docs"
Requires-Dist: scikit-learn; extra == "docs"
Requires-Dist: scikit-image; extra == "docs"
Requires-Dist: sphinx; extra == "docs"
Requires-Dist: sphinx-gallery; extra == "docs"
Requires-Dist: geoh5py; extra == "docs"
Requires-Dist: geopandas; extra == "docs"
Requires-Dist: sphinxcontrib-bibtex; extra == "docs"
Requires-Dist: myst-parser; extra == "docs"
Requires-Dist: sphinx-design; extra == "docs"
Dynamic: license-file
